ua_datasets/__init__.py
ua_datasets/question_answering/__init__.py
ua_datasets/question_answering/uasquad_question_answering.py
ua_datasets/question_answering/utils.py
ua_datasets/text_classification/__init__.py
ua_datasets/text_classification/news_classification.py
ua_datasets/token_classification/__init__.py
ua_datasets/token_classification/part_of_speech.py
ua_datasets-0.1.2.dist-info/LICENSE
ua_datasets-0.1.2.dist-info/METADATA
ua_datasets-0.1.2.dist-info/WHEEL
ua_datasets-0.1.2.dist-info/top_level.txt
ua_datasets-0.1.2.dist-info/RECORD
