Metadata-Version: 2.1
Name: ua-datasets
Version: 0.1.2
Summary: A collection of ukrainian language datasets
Home-page: https://github.com/fido-ai/ua-datasets
Author: FIdo AI
Author-email: FIdo AI <ivanyuk.skulskiy@ukma.edu.ua>
License: MIT License
Project-URL: repository, https://github.com/fido-ai/ua-datasets
Keywords: ua-datasets
Classifier: Intended Audience :: Developers
Classifier: Intended Audience :: Education
Classifier: Intended Audience :: Science/Research
Classifier: Natural Language :: Ukrainian
Classifier: License :: OSI Approved :: MIT License
Classifier: Programming Language :: Python :: 3
Classifier: Programming Language :: Python :: 3.7
Requires-Python: >=3.7.0
License-File: LICENSE
